README.md
setup.py
dcaeapplib/__init__.py
dcaeapplib.egg-info/PKG-INFO
dcaeapplib.egg-info/SOURCES.txt
dcaeapplib.egg-info/dependency_links.txt
dcaeapplib.egg-info/entry_points.txt
dcaeapplib.egg-info/requires.txt
dcaeapplib.egg-info/top_level.txt
dcaeapplib.egg-info/zip-safe