Metadata-Version: 1.0
Name: dcaeapplib
Version: 0.0.5
Summary: Library for building DCAE analytics applications
Home-page: UNKNOWN
Author: Andrew Gauld
Author-email: ag1282@att.com
License: Apache 2.0
Platform: UNKNOWN
